star_openapi/__init__.py
star_openapi/__main__.py
star_openapi/__version__.py
star_openapi/cli.py
star_openapi/config.py
star_openapi/endpoint.py
star_openapi/openapi.py
star_openapi/plugins.py
star_openapi/py.typed
star_openapi/request.py
star_openapi/router.py
star_openapi/templates.py
star_openapi/types.py
star_openapi/utils.py
star_openapi/models/__init__.py
star_openapi/models/callback.py
star_openapi/models/components.py
star_openapi/models/contact.py
star_openapi/models/data_type.py
star_openapi/models/discriminator.py
star_openapi/models/encoding.py
star_openapi/models/example.py
star_openapi/models/external_documentation.py
star_openapi/models/file.py
star_openapi/models/header.py
star_openapi/models/info.py
star_openapi/models/license.py
star_openapi/models/link.py
star_openapi/models/media_type.py
star_openapi/models/oauth_flow.py
star_openapi/models/oauth_flows.py
star_openapi/models/operation.py
star_openapi/models/parameter.py
star_openapi/models/parameter_in_type.py
star_openapi/models/path_item.py
star_openapi/models/paths.py
star_openapi/models/reference.py
star_openapi/models/request_body.py
star_openapi/models/response.py
star_openapi/models/responses.py
star_openapi/models/schema.py
star_openapi/models/security_requirement.py
star_openapi/models/security_scheme.py
star_openapi/models/security_scheme_in_type.py
star_openapi/models/server.py
star_openapi/models/server_variable.py
star_openapi/models/style_values.py
star_openapi/models/tag.py
star_openapi/models/validation_error.py
star_openapi/models/xml.py
star_openapi-0.9.2.dist-info/METADATA
star_openapi-0.9.2.dist-info/WHEEL
star_openapi-0.9.2.dist-info/entry_points.txt
star_openapi-0.9.2.dist-info/licenses/LICENSE
star_openapi-0.9.2.dist-info/RECORD
